{
  "elements": [
    {
      "first": "minecraft:oak_planks",
      "second": "shrines:plank"
    },
    {
      "first": "minecraft:oak_slab",
      "second": "shrines:slab"
    },
    {
      "first": "minecraft:oak_button",
      "second": "shrines:button"
    },
    {
      "first": "minecraft:oak_stairs",
      "second": "shrines:stairs"
    },
    {
      "first": "minecraft:oak_fence",
      "second": "shrines:fence"
    },
    {
      "first": "minecraft:oak_fence_gate",
      "second": "shrines:fence_gate"
    },
    {
      "first": "minecraft:oak_log",
      "second": "shrines:log"
    },
    {
      "first": "minecraft:stripped_oak_log",
      "second": "shrines:stripped_log"
    },
    {
      "first": "minecraft:oak_trapdoor",
      "second": "shrines:trapdoor"
    },
    {
      "first": "minecraft:oak_door",
      "second": "shrines:door"
    },
    {
      "first": "minecraft:oak_sign",
      "second": "shrines:standing_sign"
    },
    {
      "first": "minecraft:oak_wall_sign",
      "second": "shrines:wall_sign"
    },
    {
      "first": "minecraft:oak_leaves",
      "second": "shrines:leaves"
    },
    {
      "first": "minecraft:oak_wood",
      "second": "shrines:wood"
    }
  ]
}